README.md
setup.cfg
setup.py
pymsteams/__init__.py
pymsteams.egg-info/PKG-INFO
pymsteams.egg-info/SOURCES.txt
pymsteams.egg-info/dependency_links.txt
pymsteams.egg-info/requires.txt
pymsteams.egg-info/top_level.txt